img_resizer/__init__.py
img_resizer/resize.py
img_resize-0.0.2.dist-info/METADATA
img_resize-0.0.2.dist-info/WHEEL
img_resize-0.0.2.dist-info/top_level.txt
img_resize-0.0.2.dist-info/RECORD
